pyqt_spellcheck/__init__.py
pyqt_spellcheck/correction_action.py
pyqt_spellcheck/highlighter.py
pyqt_spellcheck/spellcheckwrapper.py
pyqt_spellcheck/spelllineedit.py
pyqt_spellcheck/spelltextedit.py
pyqt_spellcheck/util.py
pyqt_spellcheck-0.2.1.dist-info/LICENSE
pyqt_spellcheck-0.2.1.dist-info/METADATA
pyqt_spellcheck-0.2.1.dist-info/WHEEL
pyqt_spellcheck-0.2.1.dist-info/RECORD
